airtable/__init__.py
airtable/__init__.pyi
airtable/airtable.py
airtable/airtable.pyi
airtable/py.typed
airtable-0.4.8.dist-info/AUTHORS
airtable-0.4.8.dist-info/METADATA
airtable-0.4.8.dist-info/WHEEL
airtable-0.4.8.dist-info/pbr.json
airtable-0.4.8.dist-info/top_level.txt
airtable-0.4.8.dist-info/RECORD
